{
  "ar": [
    "media_diveScan_scanTooltip",
    "media_diveScan_noPhotosFound",
    "media_diveScan_accessDenied",
    "media_diveScan_foundPhotos",
    "media_diveScan_foundTitle",
    "media_diveScan_linkButton",
    "media_diveScan_cancelButton",
    "media_diveScan_error",
    "settings_appearance_metricsEnabledCount",
    "trips_diveScan_addButton",
    "trips_diveScan_added",
    "trips_diveScan_cancel",
    "trips_diveScan_currentTrip",
    "trips_diveScan_deselectAll",
    "trips_diveScan_error",
    "trips_diveScan_findButton",
    "trips_diveScan_groupOtherTrips",
    "trips_diveScan_groupUnassigned",
    "trips_diveScan_noMatches",
    "trips_diveScan_selectAll",
    "trips_diveScan_subtitle",
    "trips_diveScan_title",
    "trips_diveScan_unknownSite",
    "diveImport_healthkit_attribution",
    "diveImport_healthkit_dataUsage"
  ],

  "de": [
    "media_diveScan_scanTooltip",
    "media_diveScan_noPhotosFound",
    "media_diveScan_accessDenied",
    "media_diveScan_foundPhotos",
    "media_diveScan_foundTitle",
    "media_diveScan_linkButton",
    "media_diveScan_cancelButton",
    "media_diveScan_error",
    "settings_appearance_metricsEnabledCount",
    "trips_diveScan_addButton",
    "trips_diveScan_added",
    "trips_diveScan_cancel",
    "trips_diveScan_currentTrip",
    "trips_diveScan_deselectAll",
    "trips_diveScan_error",
    "trips_diveScan_findButton",
    "trips_diveScan_groupOtherTrips",
    "trips_diveScan_groupUnassigned",
    "trips_diveScan_noMatches",
    "trips_diveScan_selectAll",
    "trips_diveScan_subtitle",
    "trips_diveScan_title",
    "trips_diveScan_unknownSite",
    "diveImport_healthkit_attribution",
    "diveImport_healthkit_dataUsage"
  ],

  "es": [
    "media_diveScan_scanTooltip",
    "media_diveScan_noPhotosFound",
    "media_diveScan_accessDenied",
    "media_diveScan_foundPhotos",
    "media_diveScan_foundTitle",
    "media_diveScan_linkButton",
    "media_diveScan_cancelButton",
    "media_diveScan_error",
    "settings_appearance_metricsEnabledCount",
    "trips_diveScan_addButton",
    "trips_diveScan_added",
    "trips_diveScan_cancel",
    "trips_diveScan_currentTrip",
    "trips_diveScan_deselectAll",
    "trips_diveScan_error",
    "trips_diveScan_findButton",
    "trips_diveScan_groupOtherTrips",
    "trips_diveScan_groupUnassigned",
    "trips_diveScan_noMatches",
    "trips_diveScan_selectAll",
    "trips_diveScan_subtitle",
    "trips_diveScan_title",
    "trips_diveScan_unknownSite",
    "diveImport_healthkit_attribution",
    "diveImport_healthkit_dataUsage"
  ],

  "fr": [
    "media_diveScan_scanTooltip",
    "media_diveScan_noPhotosFound",
    "media_diveScan_accessDenied",
    "media_diveScan_foundPhotos",
    "media_diveScan_foundTitle",
    "media_diveScan_linkButton",
    "media_diveScan_cancelButton",
    "media_diveScan_error",
    "settings_appearance_metricsEnabledCount",
    "trips_diveScan_addButton",
    "trips_diveScan_added",
    "trips_diveScan_cancel",
    "trips_diveScan_currentTrip",
    "trips_diveScan_deselectAll",
    "trips_diveScan_error",
    "trips_diveScan_findButton",
    "trips_diveScan_groupOtherTrips",
    "trips_diveScan_groupUnassigned",
    "trips_diveScan_noMatches",
    "trips_diveScan_selectAll",
    "trips_diveScan_subtitle",
    "trips_diveScan_title",
    "trips_diveScan_unknownSite",
    "diveImport_healthkit_attribution",
    "diveImport_healthkit_dataUsage"
  ],

  "he": [
    "media_diveScan_scanTooltip",
    "media_diveScan_noPhotosFound",
    "media_diveScan_accessDenied",
    "media_diveScan_foundPhotos",
    "media_diveScan_foundTitle",
    "media_diveScan_linkButton",
    "media_diveScan_cancelButton",
    "media_diveScan_error",
    "settings_appearance_metricsEnabledCount",
    "trips_diveScan_addButton",
    "trips_diveScan_added",
    "trips_diveScan_cancel",
    "trips_diveScan_currentTrip",
    "trips_diveScan_deselectAll",
    "trips_diveScan_error",
    "trips_diveScan_findButton",
    "trips_diveScan_groupOtherTrips",
    "trips_diveScan_groupUnassigned",
    "trips_diveScan_noMatches",
    "trips_diveScan_selectAll",
    "trips_diveScan_subtitle",
    "trips_diveScan_title",
    "trips_diveScan_unknownSite",
    "diveImport_healthkit_attribution",
    "diveImport_healthkit_dataUsage"
  ],

  "hu": [
    "media_diveScan_scanTooltip",
    "media_diveScan_noPhotosFound",
    "media_diveScan_accessDenied",
    "media_diveScan_foundPhotos",
    "media_diveScan_foundTitle",
    "media_diveScan_linkButton",
    "media_diveScan_cancelButton",
    "media_diveScan_error",
    "settings_appearance_metricsEnabledCount",
    "trips_diveScan_addButton",
    "trips_diveScan_added",
    "trips_diveScan_cancel",
    "trips_diveScan_currentTrip",
    "trips_diveScan_deselectAll",
    "trips_diveScan_error",
    "trips_diveScan_findButton",
    "trips_diveScan_groupOtherTrips",
    "trips_diveScan_groupUnassigned",
    "trips_diveScan_noMatches",
    "trips_diveScan_selectAll",
    "trips_diveScan_subtitle",
    "trips_diveScan_title",
    "trips_diveScan_unknownSite",
    "diveImport_healthkit_attribution",
    "diveImport_healthkit_dataUsage"
  ],

  "it": [
    "media_diveScan_scanTooltip",
    "media_diveScan_noPhotosFound",
    "media_diveScan_accessDenied",
    "media_diveScan_foundPhotos",
    "media_diveScan_foundTitle",
    "media_diveScan_linkButton",
    "media_diveScan_cancelButton",
    "media_diveScan_error",
    "settings_appearance_metricsEnabledCount",
    "trips_diveScan_addButton",
    "trips_diveScan_added",
    "trips_diveScan_cancel",
    "trips_diveScan_currentTrip",
    "trips_diveScan_deselectAll",
    "trips_diveScan_error",
    "trips_diveScan_findButton",
    "trips_diveScan_groupOtherTrips",
    "trips_diveScan_groupUnassigned",
    "trips_diveScan_noMatches",
    "trips_diveScan_selectAll",
    "trips_diveScan_subtitle",
    "trips_diveScan_title",
    "trips_diveScan_unknownSite",
    "diveImport_healthkit_attribution",
    "diveImport_healthkit_dataUsage"
  ],

  "nl": [
    "media_diveScan_scanTooltip",
    "media_diveScan_noPhotosFound",
    "media_diveScan_accessDenied",
    "media_diveScan_foundPhotos",
    "media_diveScan_foundTitle",
    "media_diveScan_linkButton",
    "media_diveScan_cancelButton",
    "media_diveScan_error",
    "settings_appearance_metricsEnabledCount",
    "trips_diveScan_addButton",
    "trips_diveScan_added",
    "trips_diveScan_cancel",
    "trips_diveScan_currentTrip",
    "trips_diveScan_deselectAll",
    "trips_diveScan_error",
    "trips_diveScan_findButton",
    "trips_diveScan_groupOtherTrips",
    "trips_diveScan_groupUnassigned",
    "trips_diveScan_noMatches",
    "trips_diveScan_selectAll",
    "trips_diveScan_subtitle",
    "trips_diveScan_title",
    "trips_diveScan_unknownSite",
    "diveImport_healthkit_attribution",
    "diveImport_healthkit_dataUsage"
  ],

  "pt": [
    "media_diveScan_scanTooltip",
    "media_diveScan_noPhotosFound",
    "media_diveScan_accessDenied",
    "media_diveScan_foundPhotos",
    "media_diveScan_foundTitle",
    "media_diveScan_linkButton",
    "media_diveScan_cancelButton",
    "media_diveScan_error",
    "settings_appearance_metricsEnabledCount",
    "trips_diveScan_addButton",
    "trips_diveScan_added",
    "trips_diveScan_cancel",
    "trips_diveScan_currentTrip",
    "trips_diveScan_deselectAll",
    "trips_diveScan_error",
    "trips_diveScan_findButton",
    "trips_diveScan_groupOtherTrips",
    "trips_diveScan_groupUnassigned",
    "trips_diveScan_noMatches",
    "trips_diveScan_selectAll",
    "trips_diveScan_subtitle",
    "trips_diveScan_title",
    "trips_diveScan_unknownSite",
    "diveImport_healthkit_attribution",
    "diveImport_healthkit_dataUsage"
  ]
}
